single_hurnet/__init__.py
single_hurnet/single_hurnet.py
single_hurnet-1.0.8.dist-info/LICENSE.txt
single_hurnet-1.0.8.dist-info/METADATA
single_hurnet-1.0.8.dist-info/WHEEL
single_hurnet-1.0.8.dist-info/top_level.txt
single_hurnet-1.0.8.dist-info/RECORD
