Metadata-Version: 2.1
Name: single_hurnet
Version: 1.0.8
Summary: Example of construction of an Artificial Neural Network with the single-layer HurNet architecture for two-dimensional numerical matrices.
Home-page: https://github.com/sapiens-technology/SingleLayerHurNet
Author: SAPIENS TECHNOLOGY
License: Proprietary Software
License-File: LICENSE.txt
Requires-Dist: numpy
